cne/__init__.py
cne/choices.py
cne-0.1.4.dist-info/DESCRIPTION.rst
cne-0.1.4.dist-info/METADATA
cne-0.1.4.dist-info/metadata.json
cne-0.1.4.dist-info/RECORD
cne-0.1.4.dist-info/top_level.txt
cne-0.1.4.dist-info/WHEEL
